MANIFEST.in
setup.py
docs/HISTORY.txt
src/dolmen/__init__.py
src/dolmen.beaker.egg-info/PKG-INFO
src/dolmen.beaker.egg-info/SOURCES.txt
src/dolmen.beaker.egg-info/dependency_links.txt
src/dolmen.beaker.egg-info/namespace_packages.txt
src/dolmen.beaker.egg-info/not-zip-safe
src/dolmen.beaker.egg-info/requires.txt
src/dolmen.beaker.egg-info/top_level.txt
src/dolmen/beaker/README.txt
src/dolmen/beaker/__init__.py
src/dolmen/beaker/cache.py
src/dolmen/beaker/cache.txt
src/dolmen/beaker/configure.zcml
src/dolmen/beaker/interfaces.py
src/dolmen/beaker/meta.zcml
src/dolmen/beaker/session.py
src/dolmen/beaker/utilities.py
src/dolmen/beaker/zcml.py
src/dolmen/beaker/tests/__init__.py
src/dolmen/beaker/tests/ftesting.zcml
src/dolmen/beaker/tests/test_all.py