Metadata-Version: 2.1
Name: dolmen.beaker
Version: 0.4
Summary: An implementation of a zope session, using beaker.
Home-page: http://www.dolmen-project.org
Author: Souheil Chelfouh
Author-email: 
License: GPL
Keywords: Zope3 Session,Grok Dolmen
Platform: Any
Classifier: Development Status :: 4 - Beta
Classifier: Environment :: Web Environment
Classifier: Framework :: Zope3
Classifier: Intended Audience :: Other Audience
Classifier: License :: OSI Approved :: GNU General Public License (GPL)
Classifier: Operating System :: OS Independent
Classifier: Programming Language :: Python
Provides-Extra: test
